Akash_V1_Novacis_Test/__init__.py
Akash_V1_Novacis_Test/main.py
Akash_V1_Novacis_Test-0.0.1.dist-info/LICENSE
Akash_V1_Novacis_Test-0.0.1.dist-info/METADATA
Akash_V1_Novacis_Test-0.0.1.dist-info/WHEEL
Akash_V1_Novacis_Test-0.0.1.dist-info/top_level.txt
Akash_V1_Novacis_Test-0.0.1.dist-info/RECORD
