Metadata-Version: 2.1
Name: Akash-V1-Novacis-Test
Version: 0.0.1
Summary: Test publish
Author: Akash V Novacis
Author-email: akash.velpandiyan@novacisdigital.com
Classifier: Programming Language :: Python :: 3
Classifier: License :: OSI Approved :: MIT License
Classifier: Operating System :: OS Independent
Requires-Python: >=3.6
License-File: LICENSE
